mctech_actuator/actuator/__init__.py
mctech_actuator/actuator/actuator_router.py
mctech_actuator/actuator/route/__init__.py
mctech_actuator/actuator/route/env_route.py
mctech_actuator/actuator/route/health_route.py
mctech_actuator/actuator/route/info_route.py
mctech_actuator/actuator/route/metrics_routes.py
mctech_actuator/health/__init__.py
mctech_actuator/health/composite_health_indicator.py
mctech_actuator/health/health.py
mctech_actuator/health/health_manager.py
mctech_actuator/health/indicator.py
mctech_actuator-1.1.0.dist-info/METADATA
mctech_actuator-1.1.0.dist-info/WHEEL
mctech_actuator-1.1.0.dist-info/top_level.txt
mctech_actuator-1.1.0.dist-info/RECORD
