Metadata-Version: 2.1
Name: mctech-actuator
Version: 1.1.0
Summary: UNKNOWN
Home-page: UNKNOWN
License: UNKNOWN
Platform: UNKNOWN
Requires-Dist: log4py
Requires-Dist: fastapi
